django_remote_forms/__init__.py
django_remote_forms/fields.py
django_remote_forms/forms.py
django_remote_forms/utils.py
django_remote_forms/widgets.py
meg_django_remote_forms-1.2.1.dist-info/DESCRIPTION.rst
meg_django_remote_forms-1.2.1.dist-info/METADATA
meg_django_remote_forms-1.2.1.dist-info/RECORD
meg_django_remote_forms-1.2.1.dist-info/WHEEL
meg_django_remote_forms-1.2.1.dist-info/metadata.json
meg_django_remote_forms-1.2.1.dist-info/top_level.txt
