Metadata-Version: 2.0
Name: meg-django-remote-forms
Version: 1.2.1
Summary: A platform independent form serializer for Django.
Home-page: https://git.megsupporttools.com/misc/django-remote-forms
Author: MEG Support Tools
Author-email: info@medicaleguides.com
License: UNKNOWN
Platform: UNKNOWN
Classifier: Environment :: Web Environment
Classifier: Framework :: Django
Classifier: Intended Audience :: Developers
Classifier: Operating System :: OS Independent
Classifier: Programming Language :: Python
Classifier: Topic :: Utilities
